[
  {
  "Title": "Oppenheimer",
  "Year": "2023",
  "Rated": "R",
  "Released": "21 Jul 2023",
  "Runtime": "180 min",
  "Genre": "Biography, Drama, History",
  "Director": "Christopher Nolan",
  "Writer": "Christopher Nolan, Kai Bird, Martin Sherwin",
  "Actors": "Cillian Murphy, Emily Blunt, Matt Damon",
  "Plot": "The story of American scientist, J. Robert Oppenheimer, and his role in the development of the atomic bomb.",
  "Language": "English, German, Italian",
  "Country": "United States, United Kingdom",
  "Awards": "2 wins & 1 nomination",
  "Poster": "https://m.media-amazon.com/images/M/MV5BMDBmYTZjNjUtN2M1MS00MTQ2LTk2ODgtNzc2M2QyZGE5NTVjXkEyXkFqcGdeQXVyNzAwMjU2MTY@._V1_SX300.jpg",
  "Ratings": [
    {
      "Source": "Internet Movie Database",
      "Value": "8.6/10"
    },
    {
      "Source": "Rotten Tomatoes",
      "Value": "93%"
    },
    {
      "Source": "Metacritic",
      "Value": "88/100"
    }
  ],
  "Metascore": "88",
  "imdbRating": "8.6",
  "imdbVotes": "450,016",
  "imdbID": "tt15398776",
  "Type": "movie",
  "DVD": "N/A",
  "BoxOffice": "$322,500,125",
  "Production": "N/A",
  "Website": "N/A",
  "Response": "True"
},











{
  "Title": "Oppenheimer",
  "Rated": "R",
  "Released": "21 Jul 2023",
  "Runtime": "180 min",
  "Genre": "Biography, Drama, History",
  "Director": "Christopher Nolan",
  "Plot": "The story of American scientist, J. Robert Oppenheimer, and his role in the development of the atomic bomb.",
  "Poster": "https://m.media-amazon.com/images/M/MV5BMDBmYTZjNjUtN2M1MS00MTQ2LTk2ODgtNzc2M2QyZGE5NTVjXkEyXkFqcGdeQXVyNzAwMjU2MTY@._V1_SX300.jpg",
  "Ratings": [
    {
      "Source": "Internet Movie Database",
      "Value": "8.6/10"
    },
    {
      "Source": "Rotten Tomatoes",
      "Value": "93%"
    },
    {
      "Source": "Metacritic",
      "Value": "88/100"
    }
  ]
},





















  {
    "title": "Departed",
    "imageUrl": "https://m.media-amazon.com/images/M/MV5BMDBmYTZjNjUtN2M1MS00MTQ2LTk2ODgtNzc2M2QyZGE5NTVjXkEyXkFqcGdeQXVyNzAwMjU2MTY@._V1_SX300.jpg",
    "genres": "Biography, Drama, History",
    "released": "21 Jul 2023",
    "runtime": "180 min",
    "details": {
      "plot": "The story of American scientist, J. Robert Oppenheimer, and his role in the development of the atomic bomb.",
      "rated": "R",
      "director": "Christopher Nolan",
      "ratings": [
        {
          "ratingSource": "Internet Movie Database",
          "Value": "8.6/10"
        },
        {
          "ratingSource": "Rotten Tomatoes",
          "Value": "93%"
        },
        {
          "ratingSource": "Metacritic",
          "Value": "88/100"
        }
      ]
    },
    "availableOn": [

    ]
  }

]